new_deviantart/__init__.py
new_deviantart/api.py
new_deviantart/comment.py
new_deviantart/deviation.py
new_deviantart/message.py
new_deviantart/status.py
new_deviantart/user.py
new_deviantart-0.2.4.dist-info/LICENSE
new_deviantart-0.2.4.dist-info/METADATA
new_deviantart-0.2.4.dist-info/WHEEL
new_deviantart-0.2.4.dist-info/top_level.txt
new_deviantart-0.2.4.dist-info/RECORD
