Metadata-Version: 2.1
Name: new-deviantart
Version: 0.2.4
Summary: A Python wrapper for the DeviantArt API
Home-page: https://github.com/bugmaschine/deviantart
Author: Kevin Eichhorn
Author-email: kevineichhorn@me.com
License: MIT
License-File: LICENSE
Requires-Dist: sanction
